LICENSE.txt
MANIFEST.in
README.md
setup.cfg
setup.py
test/test.py
textalyzer/Textalyzer.py
textalyzer/__init__.py
textalyzer.egg-info/PKG-INFO
textalyzer.egg-info/SOURCES.txt
textalyzer.egg-info/dependency_links.txt
textalyzer.egg-info/requires.txt
textalyzer.egg-info/top_level.txt