Metadata-Version: 2.1
Name: textalyzer
Version: 0.1.5
Summary:  A text  analyzer for repeating and contraction characters
Home-page: https://github.com/LORD-KAY/Textalyzer
Author: Lord Kay
Author-email: offeilord@gmail.com
License: MIT
Download-URL: https://github.com/LORD-KAY/Textalyzer/releases/v0.1.5
Project-URL: Source, https://github.com/LORD-KAY/Textalyzer
Keywords: python,replacers,words,repeat,characters
Platform: UNKNOWN
Classifier: Development Status :: 3 - Alpha
Classifier: Intended Audience :: Developers
Classifier: License :: OSI Approved :: MIT License
Classifier: Programming Language :: Python :: 3
Classifier: Programming Language :: Python :: 2
